cobaan/__init__.py
pybie-1.1.2.dist-info/METADATA
pybie-1.1.2.dist-info/RECORD
pybie-1.1.2.dist-info/WHEEL
pybie-1.1.2.dist-info/top_level.txt
