Metadata-Version: 2.1
Name: pybie
Version: 1.1.2
Summary: A very simple web frameword for python
Home-page: https://github.com/Robialta/pybie
Author: Obie
Author-email: obyaltha@example.com
License: UNKNOWN
Platform: UNKNOWN
Classifier: Programming Language :: Python :: 3
Classifier: License :: OSI Approved :: MIT License
Classifier: Operating System :: OS Independent
